fiftyone_pipeline_core/__init__.py
fiftyone_pipeline_core/aspectproperty_value.py
fiftyone_pipeline_core/basiclist_evidence_keyfilter.py
fiftyone_pipeline_core/constants.py
fiftyone_pipeline_core/elementdata.py
fiftyone_pipeline_core/elementdata_dictionary.py
fiftyone_pipeline_core/evidence.py
fiftyone_pipeline_core/evidence_keyfilter.py
fiftyone_pipeline_core/flowdata.py
fiftyone_pipeline_core/flowelement.py
fiftyone_pipeline_core/flowerror.py
fiftyone_pipeline_core/javascriptbuilder.py
fiftyone_pipeline_core/jsonbundler.py
fiftyone_pipeline_core/logger.py
fiftyone_pipeline_core/messages.py
fiftyone_pipeline_core/pipeline.py
fiftyone_pipeline_core/pipelinebuilder.py
fiftyone_pipeline_core/sequenceelement.py
fiftyone_pipeline_core/setheaderelement.py
fiftyone_pipeline_core/web.py
fiftyone_pipeline_core/js_templates/JavaScriptResource.mustache
fiftyone_pipeline_core-4.5.3.dist-info/METADATA
fiftyone_pipeline_core-4.5.3.dist-info/WHEEL
fiftyone_pipeline_core-4.5.3.dist-info/top_level.txt
fiftyone_pipeline_core-4.5.3.dist-info/RECORD
