Metadata-Version: 2.4
Name: fiftyone_pipeline_core
Version: 4.5.3
Summary: This package defines the essential components of the 51Degrees Pipeline API such as flow elements, flow data and evidence. It also packages together JavaScript served by a pipeline and allows for client side requests for additional data populated by evidence from the client side.
Home-page: https://51degrees.com/
Author: 51Degrees Engineering
Author-email: engineering@51degrees.com
License: EUPL-1.2
Classifier: Development Status :: 5 - Production/Stable
Classifier: Programming Language :: Python
Classifier: License :: OSI Approved :: European Union Public Licence 1.2 (EUPL 1.2)
Classifier: Operating System :: OS Independent
Classifier: Topic :: Software Development :: Libraries :: Python Modules
Requires-Python: >=3.8
Requires-Dist: chevron
Requires-Dist: jsmin
Dynamic: author
Dynamic: author-email
Dynamic: classifier
Dynamic: description
Dynamic: description-content-type
Dynamic: home-page
Dynamic: license
Dynamic: requires-dist
Dynamic: requires-python
Dynamic: summary
